[{"id":0,"languageId":9,"description":"Inflicts damage"},{"id":1,"languageId":9,"description":"No damage; inflicts status ailment"},{"id":2,"languageId":9,"description":"No damage; lowers target's stats or raises user's stats"},{"id":3,"languageId":9,"description":"No damage; heals the user"},{"id":4,"languageId":9,"description":"Inflicts damage; inflicts status ailment"},{"id":5,"languageId":9,"description":"No damage; inflicts status ailment; raises target's stats"},{"id":6,"languageId":9,"description":"Inflicts damage; lowers target's stats"},{"id":7,"languageId":9,"description":"Inflicts damage; raises user's stats"},{"id":8,"languageId":9,"description":"Inflicts damage; absorbs damage done to heal the user"},{"id":9,"languageId":9,"description":"One-hit KO"},{"id":10,"languageId":9,"description":"Effect on the whole field"},{"id":11,"languageId":9,"description":"Effect on one side of the field"},{"id":12,"languageId":9,"description":"Forces target to switch out"},{"id":13,"languageId":9,"description":"Unique effect"}]